pycali/__init__.py
pycali/cali_ordering.py
pycali/constraints.py
pycali/exceptions.py
pycali/license.py
pycali/restrictiveness_lattice_of_status.py
pycali/vocabulary.py
pycali/examples/__init__.py
pycali/examples/compatibility_constraints.py
pycali/examples/license_constraints.py
pycali/examples/licenses/__init__.py
pycali/examples/licenses/ld_licenses_odrl.py
pycali/examples/licenses/non_valid_licenses.py
pycali/examples/licenses/rep_licenses_odrl.py
pycali/examples/restrictiveness_lattice_of_status/DL1.py
pycali/examples/restrictiveness_lattice_of_status/DL2.py
pycali/examples/restrictiveness_lattice_of_status/__init__.py
pycali/ontologies/ODRL22.py
pycali/ontologies/__init__.py
pycali/ontologies/cali_onto.py
tests/__init__.py
tests/test_cali_ordering.py
tests/test_constraints.py
tests/test_deontic_lattice.py
tests/test_license.py
tests/test_vocabulary.py
pycali-3.0.0.dist-info/LICENSE
pycali-3.0.0.dist-info/METADATA
pycali-3.0.0.dist-info/WHEEL
pycali-3.0.0.dist-info/top_level.txt
pycali-3.0.0.dist-info/RECORD
