Metadata-Version: 2.1
Name: pycali
Version: 3.0.0
Summary: A python package that defines a partial order over RDF licenses
Home-page: https://github.com/benjimor/CaLi
Author: benjimor
Author-email: benjimor44@gmail.com
License: MIT
Keywords: license,rdf,semantic web,research
Platform: UNKNOWN
Classifier: Programming Language :: Python :: 3
Classifier: License :: OSI Approved :: MIT License
Classifier: Operating System :: OS Independent
Requires-Dist: rdflib
